django_privacy_policy_tools-0.2.0.dist-info/licenses/LICENSE
privacy_policy_tools/__init__.py
privacy_policy_tools/admin.py
privacy_policy_tools/apps.py
privacy_policy_tools/context_processors.py
privacy_policy_tools/forms.py
privacy_policy_tools/middleware.py
privacy_policy_tools/models.py
privacy_policy_tools/tests.py
privacy_policy_tools/translation.py
privacy_policy_tools/urls.py
privacy_policy_tools/utils.py
privacy_policy_tools/views.py
privacy_policy_tools/migrations/0001_initial.py
privacy_policy_tools/migrations/0002_alter_privacypolicy_for_group.py
privacy_policy_tools/migrations/0003_auto_20220602_0950.py
privacy_policy_tools/migrations/0004_privacypolicy_active.py
privacy_policy_tools/migrations/0005_auto_20221216_1110.py
privacy_policy_tools/migrations/0006_auto_20230202_1159.py
privacy_policy_tools/migrations/0007_alter_privacypolicy_confirm_button_text_and_more.py
privacy_policy_tools/migrations/0008_privacypolicyconfirmation_second_confirmed_at.py
privacy_policy_tools/migrations/0009_onetimetoken.py
privacy_policy_tools/migrations/0010_alter_privacypolicy_text_alter_privacypolicy_text_de_and_more.py
privacy_policy_tools/migrations/__init__.py
django_privacy_policy_tools-0.2.0.dist-info/METADATA
django_privacy_policy_tools-0.2.0.dist-info/WHEEL
django_privacy_policy_tools-0.2.0.dist-info/top_level.txt
django_privacy_policy_tools-0.2.0.dist-info/RECORD
