Metadata-Version: 2.4
Name: django-privacy-policy-tools
Version: 0.2.0
Summary: This is a highly configurable Django app to manage privacy policies and confirmations.
Home-page: https://github.com/wachjose88/django-privacy-policy-tools
Author: Josef Wachtler
Author-email: josef.wachtler@gmail.com
Classifier: Programming Language :: Python :: 3
Classifier: Framework :: Django
Classifier: License :: OSI Approved :: MIT License
Classifier: Operating System :: OS Independent
Requires-Python: >=3.10
License-File: LICENSE
Requires-Dist: django<5.3,>=5.2.0
Requires-Dist: django-ckeditor
Requires-Dist: django-tinymce
Dynamic: author
Dynamic: author-email
Dynamic: classifier
Dynamic: description
Dynamic: description-content-type
Dynamic: home-page
Dynamic: license-file
Dynamic: requires-dist
Dynamic: requires-python
Dynamic: summary
